wecon_charset_normalizer/__init__.pyc
wecon_charset_normalizer/__main__.pyc
wecon_charset_normalizer/api.pyc
wecon_charset_normalizer/cd.pyc
wecon_charset_normalizer/constant.pyc
wecon_charset_normalizer/legacy.pyc
wecon_charset_normalizer/md.cpython-313t-arm-linux-gnueabihf.so
wecon_charset_normalizer/md.pyc
wecon_charset_normalizer/md__mypyc.cpython-313t-arm-linux-gnueabihf.so
wecon_charset_normalizer/models.pyc
wecon_charset_normalizer/py.typed
wecon_charset_normalizer/utils.pyc
wecon_charset_normalizer/version.pyc
wecon_charset_normalizer/cli/__init__.pyc
wecon_charset_normalizer/cli/__main__.pyc
wecon_charset_normalizer-3.4.2.dist-info/METADATA
wecon_charset_normalizer-3.4.2.dist-info/WHEEL
wecon_charset_normalizer-3.4.2.dist-info/top_level.txt
wecon_charset_normalizer-3.4.2.dist-info/RECORD
