Metadata-Version: 2.1
Name: wecon_charset_normalizer
Version: 3.4.2
Summary: Auto-generated package for wecon_charset_normalizer
Home-page: UNKNOWN
Author: WECON_HJB
License: UNKNOWN
Platform: linux-armv7l
Requires-Python: >=3.9
